{
  "Name": "SMS - Main Levels Shine",
  "Category": "Mario",
  "Subcategory": "Super Mario Sunshine",
  "Items": [
    {
      "Index": 1,
      "Name_FR": "La route vers le Grand Moulin",
      "Name_EN": "Road to the Big Windmill",
      "PictureMain": "https://raw.githubusercontent.com/MythMega/mythmega.github.io.assets/refs/heads/master/assets/category/mario/sms/1.png"
    },
    {
      "Index": 2,
      "Name_FR": "L'attaque de Flora Piranha",
      "Name_EN": "Down with Petey Piranha!",
      "PictureMain": "https://raw.githubusercontent.com/MythMega/mythmega.github.io.assets/refs/heads/master/assets/category/mario/sms/2.png"
    },
    {
      "Index": 3,
      "Name_FR": "Le secret de la grotte de la colline",
      "Name_EN": "The Hillside Cave Secret",
      "PictureMain": "https://raw.githubusercontent.com/MythMega/mythmega.github.io.assets/refs/heads/master/assets/category/mario/sms/3.png"
    },
    {
      "Index": 4,
      "Name_FR": "Les pièces rouges du village",
      "Name_EN": "Red Coins of Windmill Village",
      "PictureMain": "https://raw.githubusercontent.com/MythMega/mythmega.github.io.assets/refs/heads/master/assets/category/mario/sms/4.png"
    },
    {
      "Index": 5,
      "Name_FR": "Le retour de Flora Piranha",
      "Name_EN": "Petey Piranha Strikes Back",
      "PictureMain": "https://raw.githubusercontent.com/MythMega/mythmega.github.io.assets/refs/heads/master/assets/category/mario/sms/5.png"
    },
    {
      "Index": 6,
      "Name_FR": "Le secret du lac pollué",
      "Name_EN": "The Secret of the Dirty Lake",
      "PictureMain": "https://raw.githubusercontent.com/MythMega/mythmega.github.io.assets/refs/heads/master/assets/category/mario/sms/6.png"
    },
    {
      "Index": 7,
      "Name_FR": "Antimario en cavale",
      "Name_EN": "Shadow Mario on the Loose",
      "PictureMain": "https://raw.githubusercontent.com/MythMega/mythmega.github.io.assets/refs/heads/master/assets/category/mario/sms/7.png"
    },
    {
      "Index": 8,
      "Name_FR": "Les pièces rouges du lac",
      "Name_EN": "Red Coins of the Lake",
      "PictureMain": "https://raw.githubusercontent.com/MythMega/mythmega.github.io.assets/refs/heads/master/assets/category/mario/sms/8.png"
    },
    {
      "Index": 9,
      "Name_FR": "Les pièces rouges de la grotte de la colline",
      "Name_EN": "The Hillside Cave Red Coins",
      "PictureMain": "https://raw.githubusercontent.com/MythMega/mythmega.github.io.assets/refs/heads/master/assets/category/mario/sms/9.png"
    },
    {
      "Index": 10,
      "Name_FR": "Les pièces rouges du lac pollué",
      "Name_EN": "Red Coins of the Dirty Lake",
      "PictureMain": "https://raw.githubusercontent.com/MythMega/mythmega.github.io.assets/refs/heads/master/assets/category/mario/sms/10.png"
    },
    {
      "Index": 11,
      "Name_FR": "100 pièces Collines Bianco",
      "Name_EN": "Bianco Hills 100 Coin Shine",
      "PictureMain": "https://raw.githubusercontent.com/MythMega/mythmega.github.io.assets/refs/heads/master/assets/category/mario/sms/11.png"
    },
    {
      "Index": 12,
      "Name_FR": "Le Méga Bloups pollueur",
      "Name_EN": "Gooper Blooper Breaks Out",
      "PictureMain": "https://raw.githubusercontent.com/MythMega/mythmega.github.io.assets/refs/heads/master/assets/category/mario/sms/12.png"
    },
    {
      "Index": 13,
      "Name_FR": "La surf attitude",
      "Name_EN": "Blooper Surfing Safari",
      "PictureMain": "https://raw.githubusercontent.com/MythMega/mythmega.github.io.assets/refs/heads/master/assets/category/mario/sms/13.png"
    },
    {
      "Index": 14,
      "Name_FR": "Le soleil emprisonné",
      "Name_EN": "The Caged Sprite",
      "PictureMain": "https://raw.githubusercontent.com/MythMega/mythmega.github.io.assets/refs/heads/master/assets/category/mario/sms/14.png"
    },
    {
      "Index": 15,
      "Name_FR": "Le secret de la tour Ricco",
      "Name_EN": "The Secret of Ricco Tower",
      "PictureMain": "https://raw.githubusercontent.com/MythMega/mythmega.github.io.assets/refs/heads/master/assets/category/mario/sms/15.png"
    },
    {
      "Index": 16,
      "Name_FR": "Méga Bloups contre-attaque",
      "Name_EN": "Gooper Blooper Returns",
      "PictureMain": "https://raw.githubusercontent.com/MythMega/mythmega.github.io.assets/refs/heads/master/assets/category/mario/sms/16.png"
    },
    {
      "Index": 17,
      "Name_FR": "Les pièces rouges du port Ricco",
      "Name_EN": "Red Coins in the Water",
      "PictureMain": "https://raw.githubusercontent.com/MythMega/mythmega.github.io.assets/refs/heads/master/assets/category/mario/sms/17.png"
    },
    {
      "Index": 18,
      "Name_FR": "Antimario se fait arroser",
      "Name_EN": "Shadow Mario Revisited",
      "PictureMain": "https://raw.githubusercontent.com/MythMega/mythmega.github.io.assets/refs/heads/master/assets/category/mario/sms/18.png"
    },
    {
      "Index": 19,
      "Name_FR": "Insatiable Yoshi",
      "Name_EN": "Yoshi's Fruit Adventure",
      "PictureMain": "https://raw.githubusercontent.com/MythMega/mythmega.github.io.assets/refs/heads/master/assets/category/mario/sms/19.png"
    },
    {
      "Index": 20,
      "Name_FR": "Course de Bloups",
      "Name_EN": "Blooper Speed Run",
      "PictureMain": "https://raw.githubusercontent.com/MythMega/mythmega.github.io.assets/refs/heads/master/assets/category/mario/sms/20.png"
    },
    {
      "Index": 21,
      "Name_FR": "Les pièces rouges de la tour Ricco",
      "Name_EN": "Red Coins of Ricco Tower",
      "PictureMain": "https://raw.githubusercontent.com/MythMega/mythmega.github.io.assets/refs/heads/master/assets/category/mario/sms/21.png"
    },
    {
      "Index": 22,
      "Name_FR": "100 pièces Port Ricco",
      "Name_EN": "Ricco Harbor 100 Coin Shine",
      "PictureMain": "https://raw.githubusercontent.com/MythMega/mythmega.github.io.assets/refs/heads/master/assets/category/mario/sms/22.png"
    },
    {
      "Index": 23,
      "Name_FR": "Le secret des Fleurs des Sables",
      "Name_EN": "Dune Bud Sand Castle Secret",
      "PictureMain": "https://raw.githubusercontent.com/MythMega/mythmega.github.io.assets/refs/heads/master/assets/category/mario/sms/23.png"
    },
    {
      "Index": 24,
      "Name_FR": "Les miroirs en folie !",
      "Name_EN": "Mirror Madness! Tilt, Slam, Bam!",
      "PictureMain": "https://raw.githubusercontent.com/MythMega/mythmega.github.io.assets/refs/heads/master/assets/category/mario/sms/24.png"
    },
    {
      "Index": 25,
      "Name_FR": "Wiggler ! En avant toute !",
      "Name_EN": "Wiggler Ahoy! Full Steam Ahead!",
      "PictureMain": "https://raw.githubusercontent.com/MythMega/mythmega.github.io.assets/refs/heads/master/assets/category/mario/sms/25.png"
    },
    {
      "Index": 26,
      "Name_FR": "L'Oiseau de Sable légendaire",
      "Name_EN": "The Sand Bird is Born",
      "PictureMain": "https://raw.githubusercontent.com/MythMega/mythmega.github.io.assets/refs/heads/master/assets/category/mario/sms/26.png"
    },
    {
      "Index": 27,
      "Name_FR": "Le sprint d'Il Piantissimo",
      "Name_EN": "Il Piantissimo's Sand Sprint",
      "PictureMain": "https://raw.githubusercontent.com/MythMega/mythmega.github.io.assets/refs/heads/master/assets/category/mario/sms/27.png"
    },
    {
      "Index": 28,
      "Name_FR": "Pièces rouges et coraux",
      "Name_EN": "Red Coins in the Coral Reef",
      "PictureMain": "https://raw.githubusercontent.com/MythMega/mythmega.github.io.assets/refs/heads/master/assets/category/mario/sms/28.png"
    },
    {
      "Index": 29,
      "Name_FR": "Antimario à la plage",
      "Name_EN": "It's Shadow Mario! After Him!",
      "PictureMain": "https://raw.githubusercontent.com/MythMega/mythmega.github.io.assets/refs/heads/master/assets/category/mario/sms/29.png"
    },
    {
      "Index": 30,
      "Name_FR": "La fête des pastèques",
      "Name_EN": "The Watermelon Festival",
      "PictureMain": "https://raw.githubusercontent.com/MythMega/mythmega.github.io.assets/refs/heads/master/assets/category/mario/sms/30.png"
    },
    {
      "Index": 31,
      "Name_FR": "Les pièces rouges du château de sable",
      "Name_EN": "Dune Bud Sand Castle Red Coins",
      "PictureMain": "https://raw.githubusercontent.com/MythMega/mythmega.github.io.assets/refs/heads/master/assets/category/mario/sms/31.png"
    },
    {
      "Index": 32,
      "Name_FR": "Le secret du bourgeon de sable",
      "Name_EN": "Dune Bud Secret",
      "PictureMain": "https://raw.githubusercontent.com/MythMega/mythmega.github.io.assets/refs/heads/master/assets/category/mario/sms/32.png"
    },
    {
      "Index": 33,
      "Name_FR": "100 pièces Gelato-les-flots",
      "Name_EN": "Gelato Beach 100 Coin Shine",
      "PictureMain": "https://raw.githubusercontent.com/MythMega/mythmega.github.io.assets/refs/heads/master/assets/category/mario/sms/33.png"
    },
    {
      "Index": 34,
      "Name_FR": "L'apparition de Mecha-Bowser",
      "Name_EN": "Mecha-Bowser Appears!",
      "PictureMain": "https://raw.githubusercontent.com/MythMega/mythmega.github.io.assets/refs/heads/master/assets/category/mario/sms/34.png"
    },
    {
      "Index": 35,
      "Name_FR": "Le secret du canon de la plage",
      "Name_EN": "The Beach Cannon's Secret",
      "PictureMain": "https://raw.githubusercontent.com/MythMega/mythmega.github.io.assets/refs/heads/master/assets/category/mario/sms/35.png"
    },
    {
      "Index": 36,
      "Name_FR": "Pièces rouges et pirates",
      "Name_EN": "Red Coins of the Pirate Ships",
      "PictureMain": "https://raw.githubusercontent.com/MythMega/mythmega.github.io.assets/refs/heads/master/assets/category/mario/sms/36.png"
    },
    {
      "Index": 37,
      "Name_FR": "Les tournesols fanés",
      "Name_EN": "The Wilted Sunflowers",
      "PictureMain": "https://raw.githubusercontent.com/MythMega/mythmega.github.io.assets/refs/heads/master/assets/category/mario/sms/37.png"
    },
    {
      "Index": 38,
      "Name_FR": "La grande roue de la discorde",
      "Name_EN": "The Runaway Ferris Wheel",
      "PictureMain": "https://raw.githubusercontent.com/MythMega/mythmega.github.io.assets/refs/heads/master/assets/category/mario/sms/38.png"
    },
    {
      "Index": 39,
      "Name_FR": "Le secret du carrousel des Yoshi",
      "Name_EN": "The Yoshi-Go-Round's Secret",
      "PictureMain": "https://raw.githubusercontent.com/MythMega/mythmega.github.io.assets/refs/heads/master/assets/category/mario/sms/39.png"
    },
    {
      "Index": 40,
      "Name_FR": "Antimario prend du bon temps",
      "Name_EN": "Shadow Mario in the Park",
      "PictureMain": "https://raw.githubusercontent.com/MythMega/mythmega.github.io.assets/refs/heads/master/assets/category/mario/sms/40.png"
    },
    {
      "Index": 41,
      "Name_FR": "Les ballons des montagnes russes",
      "Name_EN": "Rollar Coaster Balloons",
      "PictureMain": "https://raw.githubusercontent.com/MythMega/mythmega.github.io.assets/refs/heads/master/assets/category/mario/sms/41.png"
    },
    {
      "Index": 42,
      "Name_FR": "Les pièces rouges du canon de la plage",
      "Name_EN": "The Beach Cannon's Red Coins",
      "PictureMain": "https://raw.githubusercontent.com/MythMega/mythmega.github.io.assets/refs/heads/master/assets/category/mario/sms/42.png"
    },
    {
      "Index": 43,
      "Name_FR": "Les pièces rouges du carrousel des Yoshi",
      "Name_EN": "The Yoshi-Go-Round's Red Coins",
      "PictureMain": "https://raw.githubusercontent.com/MythMega/mythmega.github.io.assets/refs/heads/master/assets/category/mario/sms/43.png"
    },
    {
      "Index": 44,
      "Name_FR": "100 pièces Parc Pinna",
      "Name_EN": "Pinna Park 100 Coin Shine",
      "PictureMain": "https://raw.githubusercontent.com/MythMega/mythmega.github.io.assets/refs/heads/master/assets/category/mario/sms/44.png"
    },
    {
      "Index": 45,
      "Name_FR": "La tempête de Méga Manta",
      "Name_EN": "The Manta Storm",
      "PictureMain": "https://raw.githubusercontent.com/MythMega/mythmega.github.io.assets/refs/heads/master/assets/category/mario/sms/45.png"
    },
    {
      "Index": 46,
      "Name_FR": "Le secret du hall de l'hôtel",
      "Name_EN": "The Hotel Lobby's Secret",
      "PictureMain": "https://raw.githubusercontent.com/MythMega/mythmega.github.io.assets/refs/heads/master/assets/category/mario/sms/46.png"
    },
    {
      "Index": 47,
      "Name_FR": "Mystérieux hôtel Delfino",
      "Name_EN": "Mysterious Hotel Delfino",
      "PictureMain": "https://raw.githubusercontent.com/MythMega/mythmega.github.io.assets/refs/heads/master/assets/category/mario/sms/47.png"
    },
    {
      "Index": 48,
      "Name_FR": "Le secret du casino",
      "Name_EN": "The Secret of Casino Delfino",
      "PictureMain": "https://raw.githubusercontent.com/MythMega/mythmega.github.io.assets/refs/heads/master/assets/category/mario/sms/48.png"
    },
    {
      "Index": 49,
      "Name_FR": "Le roi Boo",
      "Name_EN": "\"impair et gagne",
      "PictureMain": "https://raw.githubusercontent.com/MythMega/mythmega.github.io.assets/refs/heads/master/assets/category/mario/sms/49.png"
    },
    {
      "Index": 50,
      "Name_FR": "Nettoyage de printemps à Sirena",
      "Name_EN": "Scrubbing Sirena Beach",
      "PictureMain": "https://raw.githubusercontent.com/MythMega/mythmega.github.io.assets/refs/heads/master/assets/category/mario/sms/50.png"
    },
    {
      "Index": 51,
      "Name_FR": "L'insaisissable Antimario",
      "Name_EN": "Shadow Mario Checks In",
      "PictureMain": "https://raw.githubusercontent.com/MythMega/mythmega.github.io.assets/refs/heads/master/assets/category/mario/sms/51.png"
    },
    {
      "Index": 52,
      "Name_FR": "Les pièces rouges de l'hôtel",
      "Name_EN": "Red Coins in the Hotel",
      "PictureMain": "https://raw.githubusercontent.com/MythMega/mythmega.github.io.assets/refs/heads/master/assets/category/mario/sms/52.png"
    },
    {
      "Index": 53,
      "Name_FR": "Les pièces rouges du hall de l'hôtel",
      "Name_EN": "The Hotel Lobby's Red Coins",
      "PictureMain": "https://raw.githubusercontent.com/MythMega/mythmega.github.io.assets/refs/heads/master/assets/category/mario/sms/53.png"
    },
    {
      "Index": 54,
      "Name_FR": "Les pièces rouges du casino",
      "Name_EN": "The Red Coins of Casino Delfino",
      "PictureMain": "https://raw.githubusercontent.com/MythMega/mythmega.github.io.assets/refs/heads/master/assets/category/mario/sms/54.png"
    },
    {
      "Index": 55,
      "Name_FR": "100 pièces Plage Sirena",
      "Name_EN": "Sirena Beach 100 Coin Shine",
      "PictureMain": "https://raw.githubusercontent.com/MythMega/mythmega.github.io.assets/refs/heads/master/assets/category/mario/sms/55.png"
    },
    {
      "Index": 56,
      "Name_FR": "Le gardien du bouchon",
      "Name_EN": "Uncork the Waterfall",
      "PictureMain": "https://raw.githubusercontent.com/MythMega/mythmega.github.io.assets/refs/heads/master/assets/category/mario/sms/56.png"
    },
    {
      "Index": 57,
      "Name_FR": "Le boss des ruines piégées",
      "Name_EN": "The Boss of Tricky Ruins",
      "PictureMain": "https://raw.githubusercontent.com/MythMega/mythmega.github.io.assets/refs/heads/master/assets/category/mario/sms/57.png"
    },
    {
      "Index": 58,
      "Name_FR": "Les pièces rouges de la bouteille",
      "Name_EN": "Red Coins in a Bottle",
      "PictureMain": "https://raw.githubusercontent.com/MythMega/mythmega.github.io.assets/refs/heads/master/assets/category/mario/sms/58.png"
    },
    {
      "Index": 59,
      "Name_FR": "La carie d'Anguy",
      "Name_EN": "Eely-Mouth's Dentist",
      "PictureMain": "https://raw.githubusercontent.com/MythMega/mythmega.github.io.assets/refs/heads/master/assets/category/mario/sms/59.png"
    },
    {
      "Index": 60,
      "Name_FR": "La baignade d'Il Piantissimo",
      "Name_EN": "Il Piantissimo's Surf Swim",
      "PictureMain": "https://raw.githubusercontent.com/MythMega/mythmega.github.io.assets/refs/heads/master/assets/category/mario/sms/60.png"
    },
    {
      "Index": 61,
      "Name_FR": "Le secret du coquillage",
      "Name_EN": "The Shell's Secret",
      "PictureMain": "https://raw.githubusercontent.com/MythMega/mythmega.github.io.assets/refs/heads/master/assets/category/mario/sms/61.png"
    },
    {
      "Index": 62,
      "Name_FR": "Antimario crapahute",
      "Name_EN": "Hold it, Shadow Mario!",
      "PictureMain": "https://raw.githubusercontent.com/MythMega/mythmega.github.io.assets/refs/heads/master/assets/category/mario/sms/62.png"
    },
    {
      "Index": 63,
      "Name_FR": "Le poisson \"pièce\" rouge",
      "Name_EN": "The Red Coin Fish",
      "PictureMain": "https://raw.githubusercontent.com/MythMega/mythmega.github.io.assets/refs/heads/master/assets/category/mario/sms/63.png"
    },
    {
      "Index": 64,
      "Name_FR": "Les pièces rouges du coquillage",
      "Name_EN": "The Shell's Red Coins",
      "PictureMain": "https://raw.githubusercontent.com/MythMega/mythmega.github.io.assets/refs/heads/master/assets/category/mario/sms/64.png"
    },
    {
      "Index": 65,
      "Name_FR": "Oiseau doré de la Baie Noki",
      "Name_EN": "Gold Bird of Noki Bay",
      "PictureMain": "https://raw.githubusercontent.com/MythMega/mythmega.github.io.assets/refs/heads/master/assets/category/mario/sms/65.png"
    },
    {
      "Index": 66,
      "Name_FR": "100 pièces Baie Noki",
      "Name_EN": "Noki Bay 100 Coin Shine",
      "PictureMain": "https://raw.githubusercontent.com/MythMega/mythmega.github.io.assets/refs/heads/master/assets/category/mario/sms/66.png"
    },
    {
      "Index": 67,
      "Name_FR": "Les Chompis se déchaînent",
      "Name_EN": "Chain Chomplets Unchained",
      "PictureMain": "https://raw.githubusercontent.com/MythMega/mythmega.github.io.assets/refs/heads/master/assets/category/mario/sms/67.png"
    },
    {
      "Index": 68,
      "Name_FR": "Il Piantissimo prend de la hauteur",
      "Name_EN": "Il Piantissimo's Crazy Climb",
      "PictureMain": "https://raw.githubusercontent.com/MythMega/mythmega.github.io.assets/refs/heads/master/assets/category/mario/sms/68.png"
    },
    {
      "Index": 69,
      "Name_FR": "Le sauvetage du maire",
      "Name_EN": "The Goopy Inferno",
      "PictureMain": "https://raw.githubusercontent.com/MythMega/mythmega.github.io.assets/refs/heads/master/assets/category/mario/sms/69.png"
    },
    {
      "Index": 70,
      "Name_FR": "Le bain du Chomp déchaîné",
      "Name_EN": "Chain Chomp's Bath",
      "PictureMain": "https://raw.githubusercontent.com/MythMega/mythmega.github.io.assets/refs/heads/master/assets/category/mario/sms/70.png"
    },
    {
      "Index": 71,
      "Name_FR": "Le secret du monde du dessous",
      "Name_EN": "Secret of the Village Underside",
      "PictureMain": "https://raw.githubusercontent.com/MythMega/mythmega.github.io.assets/refs/heads/master/assets/category/mario/sms/71.png"
    },
    {
      "Index": 72,
      "Name_FR": "Les dix Pianta en danger",
      "Name_EN": "Piantas in Need",
      "PictureMain": "https://raw.githubusercontent.com/MythMega/mythmega.github.io.assets/refs/heads/master/assets/category/mario/sms/72.png"
    },
    {
      "Index": 73,
      "Name_FR": "À la poursuite d'Antimario",
      "Name_EN": "Shadow Mario Runs Wild",
      "PictureMain": "https://raw.githubusercontent.com/MythMega/mythmega.github.io.assets/refs/heads/master/assets/category/mario/sms/73.png"
    },
    {
      "Index": 74,
      "Name_FR": "Les pièces rouges des Pianta",
      "Name_EN": "Fluff Festival Coin Hunt",
      "PictureMain": "https://raw.githubusercontent.com/MythMega/mythmega.github.io.assets/refs/heads/master/assets/category/mario/sms/74.png"
    },
    {
      "Index": 75,
      "Name_FR": "Les pièces rouges du monde du dessous",
      "Name_EN": "Red Coins of the Village Underside",
      "PictureMain": "https://raw.githubusercontent.com/MythMega/mythmega.github.io.assets/refs/heads/master/assets/category/mario/sms/75.png"
    },
    {
      "Index": 76,
      "Name_FR": "Plus brillant que le soleil",
      "Name_EN": "Brighter than the Sun",
      "PictureMain": "https://raw.githubusercontent.com/MythMega/mythmega.github.io.assets/refs/heads/master/assets/category/mario/sms/76.png"
    },
    {
      "Index": 77,
      "Name_FR": "100 pièces Village Pianta",
      "Name_EN": "Pianta Village 100 Coin Shine",
      "PictureMain": "https://raw.githubusercontent.com/MythMega/mythmega.github.io.assets/refs/heads/master/assets/category/mario/sms/77.png"
    }
  ]
}